pymonics/Memo_esprit.py
pymonics/Passive_filters.py
pymonics/Signal_generator.py
pymonics/__init__.py
pymonics-0.3.dist-info/LICENSE
pymonics-0.3.dist-info/METADATA
pymonics-0.3.dist-info/WHEEL
pymonics-0.3.dist-info/top_level.txt
pymonics-0.3.dist-info/RECORD
